agentdesk/__init__.py
agentdesk/cli/main.py
agentdesk/config.py
agentdesk/db/conn.py
agentdesk/db/models.py
agentdesk/device.py
agentdesk/device_v1.py
agentdesk/key.py
agentdesk/processors/__init__.py
agentdesk/processors/base.py
agentdesk/processors/grid.py
agentdesk/proxy.py
agentdesk/runtime/__init__.py
agentdesk/runtime/base.py
agentdesk/runtime/docker.py
agentdesk/runtime/ec2.py
agentdesk/runtime/gce.py
agentdesk/runtime/img.py
agentdesk/runtime/kube.py
agentdesk/runtime/load.py
agentdesk/runtime/qemu.py
agentdesk/server/models.py
agentdesk/server/server.py
agentdesk/util.py
agentdesk-0.2.137.dist-info/LICENSE
agentdesk-0.2.137.dist-info/METADATA
agentdesk-0.2.137.dist-info/WHEEL
agentdesk-0.2.137.dist-info/entry_points.txt
agentdesk-0.2.137.dist-info/RECORD
