Metadata-Version: 2.1
Name: agentdesk
Version: 0.2.137
Summary: A desktop for AI agents
License: MIT
Author: Patrick Barker
Author-email: patrickbarkerco@gmail.com
Requires-Python: >=3.10,<4.0
Classifier: License :: OSI Approved :: MIT License
Classifier: Programming Language :: Python :: 3
Classifier: Programming Language :: Python :: 3.10
Classifier: Programming Language :: Python :: 3.11
Classifier: Programming Language :: Python :: 3.12
Requires-Dist: boto3 (>=1.34.28,<2.0.0)
Requires-Dist: boto3-stubs[ec2] (>=1.34.28,<2.0.0)
Requires-Dist: devicebay (>=0.1.28,<0.2.0)
Requires-Dist: docker (>=7.0.0,<8.0.0)
Requires-Dist: fastapi[all] (>=0.109.0,<0.110.0)
Requires-Dist: google-cloud-compute (>=1.15.0,<2.0.0)
Requires-Dist: google-cloud-container (>=2.38.0,<3.0.0)
Requires-Dist: google-cloud-storage (>=2.14.0,<3.0.0)
Requires-Dist: kubernetes (>=31.0.0,<32.0.0)
Requires-Dist: mypy-boto3-ec2 (>=1.34.52,<2.0.0)
Requires-Dist: namesgenerator (>=0.3,<0.4)
Requires-Dist: paramiko (>=3.4.0,<4.0.0)
Requires-Dist: pillow (==10.4.0)
Requires-Dist: psutil (>=5.9.8,<6.0.0)
Requires-Dist: psycopg2-binary (>=2.9.9,<3.0.0)
Requires-Dist: pycdlib (>=1.14.0,<2.0.0)
Requires-Dist: requests (>=2.31.0,<3.0.0)
Requires-Dist: shortuuid (>=1.0.13,<2.0.0)
Requires-Dist: sqlalchemy (>=2.0.25,<3.0.0)
Requires-Dist: tabulate (>=0.9.0,<0.10.0)
Requires-Dist: tenacity (>=8.2.3,<9.0.0)
Requires-Dist: toolfuse (>=0.1.13,<0.2.0)
Requires-Dist: tqdm (>=4.66.2,<5.0.0)
Requires-Dist: typer (>=0.9.0,<0.10.0)
